CHANGELOG.md
pycounts_polluxtroy3758/__init__.py
pycounts_polluxtroy3758/data/__init__.py
pycounts_polluxtroy3758/data/flatland.txt
pycounts_polluxtroy3758/datasets.py
pycounts_polluxtroy3758/plotting.py
pycounts_polluxtroy3758/pycounts.py
tests/einstein.txt
tests/test_pycounts_polluxtroy3758.py
pycounts_polluxtroy3758-0.3.1.dist-info/LICENSE
pycounts_polluxtroy3758-0.3.1.dist-info/WHEEL
pycounts_polluxtroy3758-0.3.1.dist-info/METADATA
pycounts_polluxtroy3758-0.3.1.dist-info/RECORD
