Metadata-Version: 2.1
Name: pycounts-polluxtroy3758
Version: 0.3.1
Summary: Calculate word counts in a text file!
License: MIT
Author: polluxtroy3758
Requires-Python: >=3.8,<4.0
Classifier: License :: OSI Approved :: MIT License
Classifier: Programming Language :: Python :: 3
Classifier: Programming Language :: Python :: 3.10
Classifier: Programming Language :: Python :: 3.8
Classifier: Programming Language :: Python :: 3.9
Requires-Dist: matplotlib (>=3.5.1,<4.0.0)
